nbdler/__init__.py
nbdler/collect.py
nbdler/exception.py
nbdler/file.py
nbdler/handler.py
nbdler/manager.py
nbdler/request.py
nbdler/saver.py
nbdler/client/__init__.py
nbdler/client/abstract_client.py
nbdler/client/http.py
nbdler/console/__init__.py
nbdler/console/abstract_console.py
nbdler/console/multi_client.py
nbdler/console/single_client.py
nbdler/struct/__init__.py
nbdler/struct/block.py
nbdler/struct/dump.py
nbdler/struct/misc.py
nbdler/struct/progress.py
nbdler/struct/signal.py
nbdler/struct/task.py
nbdler/struct/time_speed.py
nbdler/url/__init__.py
nbdler/url/basic.py
nbdler/url/pool.py
nbdler/url/response.py
nbdler/url/source.py
nbdler/utils/__init__.py
nbdler/utils/process_interface.py
nbdler/utils/thread.py
Nbdler-1.0.1.dist-info/LICENSE
Nbdler-1.0.1.dist-info/METADATA
Nbdler-1.0.1.dist-info/WHEEL
Nbdler-1.0.1.dist-info/top_level.txt
Nbdler-1.0.1.dist-info/RECORD
